es_fieldusage/__init__.py
es_fieldusage/cli.py
es_fieldusage/commands.py
es_fieldusage/defaults.py
es_fieldusage/exceptions.py
es_fieldusage/main.py
es_fieldusage/py.typed
es_fieldusage/version.py
es_fieldusage/helpers/__init__.py
es_fieldusage/helpers/utils.py
es_fieldusage-1.2.0.dist-info/METADATA
es_fieldusage-1.2.0.dist-info/WHEEL
es_fieldusage-1.2.0.dist-info/entry_points.txt
es_fieldusage-1.2.0.dist-info/licenses/LICENSE.txt
es_fieldusage-1.2.0.dist-info/RECORD
