Metadata-Version: 2.3
Name: es-fieldusage
Version: 1.2.0
Summary: Helping you determine field usage by index
Project-URL: Documentation, https://github.com/untergeek/es-fieldusage#readme
Project-URL: Issues, https://github.com/untergeek/es-fieldusage/issues
Project-URL: Source, https://github.com/untergeek/es-fieldusage
Author-email: Elastic <info@elastic.co>
License: Apache-2.0
License-File: LICENSE.txt
Keywords: elasticsearch,field,index,stats,usage
Classifier: Intended Audience :: Developers
Classifier: Intended Audience :: System Administrators
Classifier: License :: OSI Approved :: Apache Software License
Classifier: Operating System :: OS Independent
Classifier: Programming Language :: Python
Classifier: Programming Language :: Python :: 3.8
Classifier: Programming Language :: Python :: 3.9
Classifier: Programming Language :: Python :: 3.10
Classifier: Programming Language :: Python :: 3.11
Classifier: Programming Language :: Python :: 3.12
Requires-Python: >=3.8
Requires-Dist: es-client==8.17.4
Provides-Extra: doc
Requires-Dist: sphinx; extra == 'doc'
Requires-Dist: sphinx-rtd-theme; extra == 'doc'
Provides-Extra: test
Requires-Dist: mock; extra == 'test'
Requires-Dist: pytest-cov; extra == 'test'
Requires-Dist: pytest>=7.2.1; extra == 'test'
Requires-Dist: requests; extra == 'test'
